anoteai/__init__.py
anoteai/constants.py
anoteai/core.py
anoteai-0.20.dist-info/METADATA
anoteai-0.20.dist-info/WHEEL
anoteai-0.20.dist-info/top_level.txt
anoteai-0.20.dist-info/RECORD
